lab/FEC/lab2_var1/lab2_pipe.v
module lab2_pipe (
    input clk,
    input rst,
    input start,
    input [31:0] x,
    output reg rdy,
    output reg [31:0] y
);

reg [31:0] pow2, pow3, pow4, pow5, temp_pow2;
reg [31:0] x1, x2, x3, x4;
reg rdy1, rdy2;

always @(posedge clk) begin
    if (rst) begin
        y    <= 0;
        rdy  <= 1;
        pow2 <= 0;
        pow3 <= 0;
        pow4 <= 0;
        pow5 <= 0;
        x1   <= 0;
        x2   <= 0;
        x3   <= 0;
        x4   <= 0;
        rdy1 <= 0;
        rdy2 <= 0;

        temp_pow2 <= 0;
    end else begin

        if (start) begin
            rdy  <= 0;
            rdy1 <= 1;
        end

        rdy2 <= rdy1;
        rdy  <= rdy2;

        x1   <= x;
        x2   <= x1;
        x3   <= x2;
        x4   <= x3;

        pow2      <= x * x;
        pow3      <= pow2 * x1; // x ^ 3
        pow4      <= pow3 * x2; // x ^ 4
        pow5      <= pow4 * x3; // x ^ 5
        temp_pow2  = x4 * x4;   // x4 ^ 2
        y         <= pow5 + temp_pow2; // x ^ 5 + x ^ 2
    end
end
    
endmodule

lab/FEC/lab2_var1/lab2_mc.v
module lab2_mc (
    input clk,
    input rst,
    input start,
    input [31:0] x,

    output reg rdy,
    output reg [31:0] y_output
);

reg [31:0] y;
reg [31:0] x_buf;
reg [31:0] y_square;
reg [2:0] ctr;
reg [1:0] state; // 0 -> in power 2; 1 -> in power 5;
reg [2:0] current; // 0 -> multiplying; 1 -> x^2 done; 2 -> x^5 done

wire [2:0] ctr_next = (rdy)? 0: ctr + 1;
wire [31:0] y_next  = (rdy)? 1: y * x_buf;

always @(posedge clk) 
    begin
    if (rst) 
        begin
        y_output <= 0;
        y_square <= 0;
        y        <= 0;
        rdy      <= 1;
        x_buf    <= 0;
        ctr      <= 0;
        current  <= 0;
        state    <= 0;
        end 
    else 
        begin
        ctr <= ctr_next;

        if (start) 
            begin
            y        <= 1;
            rdy      <= 0;
            x_buf    <= x;
            y_square <= 0;
            state    <= 0;
            end

        if (!rdy) 
            begin
            if (ctr == 1 && state == 0)
                current <= 1;
            else if (ctr == 3 && state == 1)
                current <= 2;
            else 
                current <= 0;

            if (current == 1) 
                begin
                y_square <= y;
                y        <= 1;
                state    <= 1;
                ctr      <= 0;
                end 

            if (current == 2)
                begin
                y         = y_next + y_square;
                y_output <= y;
                rdy      <= 1;
                end

            if (current == 0)
                begin
                y        <= y_next; 
                end
            end
        end
    end

endmodule

lab/FEC/lab2_var1/lab2_oc.v
module lab2_oc (
    input clk,
    input rst,
    input [31:0] x,
    output reg [31:0] y
);
    
always @(posedge clk) begin
    if (rst)
        y <= 0;
    else 
        y <= x * x + x * x * x * x * x;
end

endmodule

lab/FEC/lab2_var1/lab2_tb.v
`timescale 1ns/1ps

module lab2_tb;

reg [31:0] x;
reg rst, clk, start;
wire [31:0] y_oc, y_mc, y_pipe;
wire rdy_mc, rdy_pipe;

lab2_oc u_lab2_oc(
    .clk ( clk ),
    .rst ( rst ),
    .x   ( x   ),
    .y   ( y   )
);

// lab2_mc uut_mc(
//     .clk(clk),
//     .rst(rst),
//     .start(start),
//     .x(x),
//     .y_output(y_mc),
//     .rdy(rdy_mc)
// );

lab2_mc u_lab2_mc(
    .clk   ( clk   ),
    .rst   ( rst   ),
    .start ( start ),
    .x     ( x     ),
    .rdy   ( rdy   ),
    .y_output  ( y_mc  )
);

lab2_pipe u_lab2_pipe(
    .clk   ( clk    ),
    .rst   ( rst    ),
    .start ( start  ),
    .x     ( x      ),
    .rdy   ( rdy    ),
    .y     ( y_pipe )
);


always #5 clk = ~clk;

always @(negedge clk) 
    x = ($random % 64) & 8'hff;

initial begin
    
    $dumpfile("time.vcd");
    $dumpvars(0, lab2_tb);

    clk   = 0;
    rst   = 1;
    x     = 0;
    // for mc
    start = 0;

    #20
    rst   = 0;
    // for mc
    start = 1;

    // for mc
    #10
    start = 0;

    // mc
    #100
    start = 1;

    // mc
    #10
    start = 0;

    #100
    $finish;

end

endmodule

lab/FEC/lab2_var1/time.vcd
$date
	Sun Apr 24 16:01:11 2022
$end
$version
	Icarus Verilog
$end
$timescale
	1ps
$end
$scope module lab2_tb $end
$var wire 1 ! rdy $end
$var wire 32 " y_pipe [31:0] $end
$var wire 32 # y_mc [31:0] $end
$var wire 1 $ y $end
$var reg 1 % clk $end
$var reg 1 & rst $end
$var reg 1 ' start $end
$var reg 32 ( x [31:0] $end
$scope module u_lab2_mc $end
$var wire 1 % clk $end
$var wire 1 & rst $end
$var wire 1 ' start $end
$var wire 32 ) x [31:0] $end
$var wire 32 * y_next [31:0] $end
$var wire 3 + ctr_next [2:0] $end
$var reg 3 , ctr [2:0] $end
$var reg 3 - current [2:0] $end
$var reg 1 . rdy $end
$var reg 2 / state [1:0] $end
$var reg 32 0 x_buf [31:0] $end
$var reg 32 1 y [31:0] $end
$var reg 32 2 y_output [31:0] $end
$var reg 32 3 y_square [31:0] $end
$upscope $end
$scope module u_lab2_oc $end
$var wire 1 % clk $end
$var wire 1 & rst $end
$var wire 32 4 x [31:0] $end
$var reg 32 5 y [31:0] $end
$upscope $end
$scope module u_lab2_pipe $end
$var wire 1 % clk $end
$var wire 1 & rst $end
$var wire 1 ' start $end
$var wire 32 6 x [31:0] $end
$var reg 32 7 pow2 [31:0] $end
$var reg 32 8 pow3 [31:0] $end
$var reg 32 9 pow4 [31:0] $end
$var reg 32 : pow5 [31:0] $end
$var reg 1 ; rdy $end
$var reg 1 < rdy1 $end
$var reg 1 = rdy2 $end
$var reg 32 > temp_pow2 [31:0] $end
$var reg 32 ? x1 [31:0] $end
$var reg 32 @ x2 [31:0] $end
$var reg 32 A x3 [31:0] $end
$var reg 32 B x4 [31:0] $end
$var reg 32 C y [31:0] $end
$upscope $end
$upscope $end
$enddefinitions $end
#0
$dumpvars
bx C
bx B
bx A
bx @
bx ?
bx >
x=
x<
x;
bx :
bx 9
bx 8
bx 7
b100100 6
bx 5
b100100 4
bx 3
bx 2
bx 1
bx 0
bx /
x.
bx -
bx ,
bx +
bx *
b100100 )
b100100 (
0'
1&
0%
x$
bx #
bx "
x!
$end
#5000
0$
b0 +
b1 *
b0 5
b0 /
b0 -
b0 ,
b0 0
1!
1.
b0 1
b0 3
b0 #
b0 2
b0 >
0=
0<
b0 B
b0 A
b0 @
b0 ?
b0 :
b0 9
b0 8
b0 7
1;
b0 "
b0 C
1%
#10000
b1 (
b1 )
b1 4
b1 6
0%
#15000
1%
#20000
b1001 (
b1001 )
b1001 4
b1001 6
0%
1'
0&
#25000
b1 +
b1001 *
b1110011011111010 5
b1001 0
0.
b1 1
b1010001 7
b1001 ?
1<
0!
0;
1%
#30000
b100011 (
b100011 )
b100011 4
b100011 6
0%
0'
#35000
b1010001 *
b10 +
b1011011001 8
b10011001001 7
b1001 @
b100011 ?
1=
b1001 1
b1 ,
b11001000010111000001011100 5
1%
#40000
b1101 (
b1101 )
b1101 4
b1101 6
0%
#45000
b0xx +
b0x0xx0xx001 *
b1011010101100000110 5
b1010001 1
b1 -
b10 ,
b1100110100001 9
b1010011101111011 8
b10101001 7
b1001 A
b100011 @
b1101 ?
x!
1;
1%
#50000
0%
#55000
b0x001 *
b0x +
b1110011010101001 :
b101101110010111010001 9
b100010010101 8
b1001 B
b100011 A
b1101 @
b1 /
b1 1
b1010001 3
b0 -
b0 ,
1%
#60000
b100101 (
b100101 )
b100101 4
b100101 6
0%
#65000
bx *
bx +
b100001000100010000000101110 5
b0x001 1
b0x ,
b1110011011111010 "
b1110011011111010 C
b11001000010110101110010011 :
b110111110010001 9
b10101011001 7
b100011 B
b1101 A
b100101 ?
b1010001 >
1%
#70000
b10010 (
b10010 )
b10010 4
b10010 6
0%
#75000
b11001000010111000001011100 "
b11001000010111000001011100 C
b1011010101001011101 :
b1100010111011101 8
b101000100 7
b1101 B
b100101 @
b10010 ?
bx 1
bx ,
b111001101011001100100 5
b10011001001 >
1%
#80000
b1 (
b1 )
b1 4
b1 6
0%
#85000
b10 5
b1011010101100000110 "
b1011010101100000110 C
b111001001100011110001 9
b1011011001000 8
b1 7
b100101 A
b10010 @
b1 ?
b10101001 >
1%
#90000
b1101 (
b1101 )
b1101 4
b1101 6
0%
#95000
b100001000100001101011010101 :
b11001101000010000 9
b1 8
b10101001 7
b100101 B
b10010 A
b1 @
b1101 ?
b1011010101100000110 5
1%
#100000
b110110 (
b110110 )
b110110 4
b110110 6
0%
#105000
b11011010111100101100011000100 5
b100001000100010000000101110 "
b100001000100010000000101110 C
b111001101010100100000 :
b1 9
b100010010101 8
b101101100100 7
b10010 B
b1 A
b1101 @
b110110 ?
b10101011001 >
1%
#110000
b111101 (
b111101 )
b111101 4
b111101 6
0%
#115000
b111001101011001100100 "
b111001101011001100100 C
b1 :
b110111110010001 9
b100110011100011000 8
b111010001001 7
b1 B
b1101 A
b110110 @
b111101 ?
b110010010101111001001011010110 5
b101000100 >
1%
#120000
b101101 (
b101101 )
b101101 4
b101101 6
0%
#125000
b1010111111111011010011100110 5
b10 "
b10 C
b1011010101001011101 :
b100000011011111100010000 9
b110111011010100101 8
b11111101001 7
b1101 B
b110110 A
b111101 @
b101101 ?
b1 >
1%
#130000
b1100 (
b1100 )
b1100 4
b1100 6
0%
1'
#135000
b1011010101100000110 "
b1011010101100000110 C
b11011010111100100110101100000 :
b110100110100010101010001 9
b10110001111110101 8
b10010000 7
b110110 B
b111101 A
b101101 @
b1100 ?
x!
1;
b0 /
b0 3
b1100 0
bx 1
b111100110010010000 5
b10101001 >
1%
#140000
b111001 (
b111001 )
b111001 4
b111001 6
0%
0'
#145000
b100011110111010010010001001010 5
b11011010111100101100011000100 "
b11011010111100101100011000100 C
b110010010101111000010001001101 :
b1111101001001000010001 9
b11011000000 8
b110010110001 7
b111101 B
b101101 A
b1100 @
b111001 ?
b101101100100 >
1%
#150000
b110 (
b110 )
b110 4
b110 6
0%
#155000
b110010010101111001001011010110 "
b110010010101111001001011010110 C
b1010111111111010110011111101 :
b101000100000000 9
b101101001101101001 8
b100100 7
b101101 B
b1100 A
b111001 @
b110 ?
b1111010000100 5
b111010001001 >
1%
#160000
b101 (
b101 )
b101 4
b101 6
0%
#165000
b110001001110 5
b1010111111111011010011100110 "
b1010111111111011010011100110 C
b111100110000000000 :
b101000010001001001100001 9
b11011000 8
b11001 7
b1100 B
b111001 A
b110 @
b101 ?
b11111101001 >
1%
#170000
b101010 (
b101010 )
b101010 4
b101010 6
0%
#175000
b111100110010010000 "
b111100110010010000 C
b100011110111010001011110011001 :
b10100010000 9
b1111101 8
b11011100100 7
b111001 B
b110 A
b101 @
b101010 ?
b111110010100011011110000100 5
b10010000 >
1%
#180000
b100101 (
b100101 )
b100101 4
b100101 6
0%
#185000
b100001000100010000000101110 5
b100011110111010010010001001010 "
b100011110111010010010001001010 C
b1111001100000 :
b1001110001 9
b10010000101101000 8
b10101011001 7
b110 B
b101 A
b101010 @
b100101 ?
b110010110001 >
1%
#190000
b110111 (
b110111 )
b110111 4
b110111 6
0%
#195000
b1111010000100 "
b1111010000100 C
b110000110101 :
b1011110111101100010000 9
b1100010111011101 8
b101111010001 7
b101 B
b101010 A
b100101 @
b110111 ?
b11101111111111000111001101000 5
b100100 >
1%
#200000
b10010 (
b10010 )
b10010 4
b10010 6
0%
#205000
b111001101011001100100 5
b110001001110 "
b110001001110 C
b111110010100011000010100000 :
b111001001100011110001 9
b101000100111100111 8
b101000100 7
b101010 B
b100101 A
b110111 @
b10010 ?
b11001 >
1%
#210000
b1111 (
b1111 )
b1111 4
b1111 6
0%
#215000
b111110010100011011110000100 "
b111110010100011011110000100 C
b100001000100001101011010101 :
b100010111010000010100001 9
b1011011001000 8
b11100001 7
b100101 B
b110111 A
b10010 @
b1111 ?
b10111001011100110000 5
b11011100100 >
1%
#220000
b110010 (
b110010 )
b110010 4
b110010 6
0%
#225000
b10010101000000110100011100100 5
b100001000100010000000101110 "
b100001000100010000000101110 C
b11101111111111000001010010111 :
b11001101000010000 9
b110100101111 8
b100111000100 7
b110111 B
b10010 A
b1111 @
b110010 ?
b10101011001 >
1%
#230000
b1110 (
b1110 )
b1110 4
b1110 6
0%
#235000
b11101111111111000111001101000 "
b11101111111111000111001101000 C
b111001101010100100000 :
b1100010111000001 9
b11110100001001000 8
b11000100 7
b10010 B
b1111 A
b110010 @
b1110 ?
b10000011010110100100 5
b101111010001 >
1%
